aioremootio/__init__.py
aioremootio/constants.py
aioremootio/enums.py
aioremootio/errors.py
aioremootio/frames.py
aioremootio/listeners.py
aioremootio/models.py
aioremootio/remootioclient.py
aioremootio-1.0.0a21.dist-info/LICENSE
aioremootio-1.0.0a21.dist-info/METADATA
aioremootio-1.0.0a21.dist-info/WHEEL
aioremootio-1.0.0a21.dist-info/top_level.txt
aioremootio-1.0.0a21.dist-info/RECORD
