Metadata-Version: 2.1
Name: aioremootio
Version: 1.0.0a21
Summary: An asynchronous API client library for Remootio (http://www.remootio.com/)
Home-page: https://github.com/ivgg-me/aioremootio
Author: Gergö Gabor Ilyes-Veisz
Author-email: i@ivgg.me
License: UNKNOWN
Project-URL: Bug Tracker, https://github.com/ivgg-me/aioremootio/issues
Project-URL: Source, https://github.com/ivgg-me/aioremootio/
Keywords: remootio,client,library,asynchronous
Platform: UNKNOWN
Classifier: Development Status :: 3 - Alpha
Classifier: Framework :: AsyncIO
Classifier: Intended Audience :: Developers
Classifier: License :: OSI Approved :: Apache Software License
Classifier: Operating System :: OS Independent
Classifier: Programming Language :: Python :: 3.10
Classifier: Programming Language :: Python :: 3.11
Classifier: Programming Language :: Python :: 3.12
Classifier: Topic :: Home Automation
Classifier: Topic :: Software Development :: Libraries
Requires-Python: >=3.8
License-File: LICENSE
Requires-Dist: aiohttp <4,>=3.8.1
Requires-Dist: pycryptodome <3.20.0,>=3.15.0
Requires-Dist: async-class ==0.5.0
Requires-Dist: voluptuous <0.14.0,>=0.13.1
